setup.py
mongoengine_multilingual_field.egg-info/PKG-INFO
mongoengine_multilingual_field.egg-info/SOURCES.txt
mongoengine_multilingual_field.egg-info/dependency_links.txt
mongoengine_multilingual_field.egg-info/requires.txt
mongoengine_multilingual_field.egg-info/top_level.txt
multilingual_field/__init__.py
multilingual_field/fields.py