Metadata-Version: 1.1
Name: mongoengine-multilingual-field
Version: 0.4-simple
Summary: MongoEngine field to store MultilingualString class from i18n-string project
Home-page: https://github.com/lig/mongoengine-multilingual-field
Author: Serge Matveenko
Author-email: s@matveenko.ru
License: UNKNOWN
Platform: UNKNOWN
Classifier: Development Status :: 4 - Beta
Classifier: Programming Language :: Python
Classifier: License :: OSI Approved :: BSD License
